supproperty/__init__.py
supproperty/basics.py
supproperty/supproperty.py
supproperty/versioned.py
supproperty-0.1.2.dist-info/METADATA
supproperty-0.1.2.dist-info/RECORD
supproperty-0.1.2.dist-info/WHEEL
supproperty-0.1.2.dist-info/top_level.txt
