Metadata-Version: 2.1
Name: supproperty
Version: 0.1.2
Summary: Supremum property
Home-page: http://ccs.chem.ucl.ac.uk
Author: Kristof Farkas-Pall
License: UNKNOWN
Platform: UNKNOWN
Classifier: Programming Language :: Python :: 3
Classifier: License :: OSI Approved :: MIT License
Classifier: Operating System :: OS Independent
Requires: numpy
